janis_templates/__init__.py
janis_templates/__meta__.py
janis_templates/pawsey.py
janis_templates/petermac.py
janis_templates/spartan.py
janis_templates/wehi.py
janis_pipelines.templates-0.12.0.dist-info/METADATA
janis_pipelines.templates-0.12.0.dist-info/WHEEL
janis_pipelines.templates-0.12.0.dist-info/entry_points.txt
janis_pipelines.templates-0.12.0.dist-info/top_level.txt
janis_pipelines.templates-0.12.0.dist-info/RECORD
