Metadata-Version: 2.1
Name: janis-pipelines.templates
Version: 0.12.0
Summary: Janis assistant templates for Parkville
Home-page: https://github.com/PMCC-BioinformaticsCore/janis-templates
Author: Michael Franklin
Author-email: michael.franklin@petermac.org
License: GNU
Platform: UNKNOWN
Classifier: Development Status :: 2 - Pre-Alpha
Classifier: Intended Audience :: Developers
Classifier: Intended Audience :: Science/Research
Classifier: Topic :: Scientific/Engineering :: Bio-Informatics
Requires-Dist: janis-pipelines.core (>=0.10.7)
Provides-Extra: ci
Requires-Dist: keyring (==21.4.0) ; extra == 'ci'
Requires-Dist: setuptools ; extra == 'ci'
Requires-Dist: wheel ; extra == 'ci'
Requires-Dist: twine ; extra == 'ci'
